CHANGES.txt
LICENSE.txt
MANIFEST.in
README.rst
setup.py
exoCode/GUI.py
exoCode/__init__.py
exoCode/analysis_script.py
exoCode/array_processing.py
exoCode/dataAcq.py
exoCode/dataGen.py
exoCode/diffraction.py
exoCode/display.py
exoCode/final_blob_identification.py
exoCode/good_candidates.py
exoCode/img_check.py
exoCode/pixel_regions.py
exoCode/random_catalog_gen.py
exoCode/thresholding.py
exoCode/Catalogs/random_catalog_sample+1000.csv
exoCode/Catalogs/random_catalog_sample+2000.csv
exoCode/Catalogs/tam_cat_sample.csv
exoCode/Catalogs/tycho_2mass_wise_XMATCH-POS.csv
exoCode/FITS/Full_Cat/empty.txt
exoCode/FITS/RandSample-1000/empty.txt
exoCode/FITS/RandSample-2000/empty.txt
exoCode/FITS/TAM/empty.txt
exoCode/FITS/TAM/index-0/2MASS--H
exoCode/FITS/TAM/index-0/2MASS--J
exoCode/FITS/TAM/index-0/2MASS--K
exoCode/FITS/TAM/index-0/DSS--DSS1+Blue
exoCode/FITS/TAM/index-0/DSS--DSS1+Red
exoCode/FITS/TAM/index-0/DSS--DSS2+Blue
exoCode/FITS/TAM/index-0/DSS--DSS2+IR
exoCode/FITS/TAM/index-0/DSS--DSS2+Red
exoCode/FITS/TAM/index-0/WISE+(AllWISE)--w1
exoCode/FITS/TAM/index-0/WISE+(AllWISE)--w2
exoCode/FITS/TAM/index-0/WISE+(AllWISE)--w3
exoCode/FITS/TAM/index-0/WISE+(AllWISE)--w4
exoCode/FITS/TAM/index-0/stellar_coordinates.txt
exoCode/FITS/TAM/index-1/2MASS--H
exoCode/FITS/TAM/index-1/2MASS--J
exoCode/FITS/TAM/index-1/2MASS--K
exoCode/FITS/TAM/index-1/DSS--DSS2+Blue
exoCode/FITS/TAM/index-1/DSS--DSS2+IR
exoCode/FITS/TAM/index-1/DSS--DSS2+Red
exoCode/FITS/TAM/index-1/WISE+(AllWISE)--w1
exoCode/FITS/TAM/index-1/WISE+(AllWISE)--w2
exoCode/FITS/TAM/index-1/WISE+(AllWISE)--w3
exoCode/FITS/TAM/index-1/WISE+(AllWISE)--w4
exoCode/FITS/TAM/index-1/stellar_coordinates.txt
exoCode/FITS/TAM/index-10/2MASS--H
exoCode/FITS/TAM/index-10/2MASS--J
exoCode/FITS/TAM/index-10/2MASS--K
exoCode/FITS/TAM/index-10/DSS--DSS1+Blue
exoCode/FITS/TAM/index-10/DSS--DSS1+Red
exoCode/FITS/TAM/index-10/DSS--DSS2+Blue
exoCode/FITS/TAM/index-10/DSS--DSS2+IR
exoCode/FITS/TAM/index-10/DSS--DSS2+Red
exocode.egg-info/PKG-INFO
exocode.egg-info/SOURCES.txt
exocode.egg-info/dependency_links.txt
exocode.egg-info/not-zip-safe
exocode.egg-info/requires.txt
exocode.egg-info/top_level.txt